csmxcrypt/__init__.py
csmxcrypt/csmxcore.py
csmxcrypt/csmxhash.py
csmxcrypt/csmximage.py
csmxcrypt/csmxkey.py
csmxcrypt/csmxstealth.py
tests/__init__.py
tests/test_csmxcrypt.py
csmxcrypt-1.0.0.dist-info/METADATA
csmxcrypt-1.0.0.dist-info/WHEEL
csmxcrypt-1.0.0.dist-info/top_level.txt
csmxcrypt-1.0.0.dist-info/RECORD
