Metadata-Version: 2.1
Name: csmxcrypt
Version: 1.0.0
Summary: AI-proof, post-quantum cryptographic encryption library
Home-page: https://github.com/Sumedh1599/csmxcrypt
Author: Sumedh Patil
Author-email: admin@aipresso.uk
License: UNKNOWN
Platform: UNKNOWN
Classifier: Programming Language :: Python :: 3
Classifier: License :: OSI Approved :: MIT License
Classifier: Operating System :: OS Independent
Requires-Python: >=3.6
Requires-Dist: pillow
Requires-Dist: numpy
